dask_gateway_eks/__init__.py
dask_gateway_eks/api.py
dask_gateway_eks/certificates.py
dask_gateway_eks/cluster.py
dask_gateway_eks/config_utils.py
dask_gateway_eks/k8s.py
dask_gateway_eks/models.py
dask_gateway_eks/scheduler_coms.py
dask_gateway_eks-0.1.0.dist-info/WHEEL
dask_gateway_eks-0.1.0.dist-info/METADATA
dask_gateway_eks-0.1.0.dist-info/RECORD
