Metadata-Version: 2.1
Name: dask-gateway-eks
Version: 0.1.0
Summary: 
Author: Tom Forbes
Author-email: tom@tomforb.es
Requires-Python: >=3.8,<4.0
Classifier: Programming Language :: Python :: 3
Classifier: Programming Language :: Python :: 3.10
Classifier: Programming Language :: Python :: 3.8
Classifier: Programming Language :: Python :: 3.9
Provides-Extra: server
Requires-Dist: backoff (>=1.0,<2.0); extra == "server"
Requires-Dist: boto3
Requires-Dist: boto3-stubs[iam]
Requires-Dist: cryptography (>=35.0.0,<36.0.0); extra == "server"
Requires-Dist: dask-gateway (>=0.9.0,<0.10.0)
Requires-Dist: fastapi (>=0.70.0,<0.71.0); extra == "server"
Requires-Dist: kubernetes_asyncio (>=18.20.0,<19.0.0); extra == "server"
Requires-Dist: sentry-sdk (>=1.0.0,<2.0.0); extra == "server"
Requires-Dist: uvicorn[standard] (>=0.15.0,<0.16.0); extra == "server"
